Metadata-Version: 2.1
Name: hazedumper
Version: 1.0.1
Summary: pkg for auto update offsets
Home-page: https://github.com/cxldxice/hazedumper
Author: cxldxice
Author-email: cxldxfxtxre@gmail.com
License: MIT
Keywords: hazedumper,offsets,csgo
Platform: UNKNOWN
License-File: LICENSE.txt
